{
  "minecraft:recipes/building_blocks/red_nether_bricks": {
    "criteria": {
      "has_nether_wart": "2021-09-05 19:16:25 +0000"
    },
    "done": true
  },
  "minecraft:recipes/misc/iron_nugget_from_blasting": {
    "criteria": {
      "has_iron_hoe": "2021-09-05 19:21:18 +0000"
    },
    "done": true
  },
  "minecraft:recipes/food/cooked_porkchop_from_campfire_cooking": {
    "criteria": {
      "has_porkchop": "2021-09-05 19:15:55 +0000"
    },
    "done": true
  },
  "minecraft:recipes/food/pumpkin_pie": {
    "criteria": {
      "has_pumpkin": "2021-09-05 19:18:16 +0000"
    },
    "done": true
  },
  "minecraft:recipes/transportation/dark_oak_boat": {
    "criteria": {
      "in_water": "2021-09-05 19:21:36 +0000"
    },
    "done": true
  },
  "minecraft:recipes/transportation/birch_boat": {
    "criteria": {
      "in_water": "2021-09-05 19:21:36 +0000"
    },
    "done": true
  },
  "minecraft:recipes/misc/gold_nugget_from_smelting": {
    "criteria": {
      "has_golden_axe": "2021-09-05 19:17:34 +0000"
    },
    "done": true
  },
  "minecraft:recipes/building_blocks/emerald_block": {
    "criteria": {
      "has_emerald": "2021-09-05 19:16:54 +0000"
    },
    "done": true
  },
  "minecraft:recipes/misc/paper": {
    "criteria": {
      "has_reeds": "2021-09-05 19:21:34 +0000"
    },
    "done": true
  },
  "minecraft:recipes/misc/sugar_from_sugar_cane": {
    "criteria": {
      "has_reeds": "2021-09-05 19:21:34 +0000"
    },
    "done": true
  },
  "minecraft:recipes/transportation/acacia_boat": {
    "criteria": {
      "in_water": "2021-09-05 19:21:36 +0000"
    },
    "done": true
  },
  "minecraft:recipes/transportation/oak_boat": {
    "criteria": {
      "in_water": "2021-09-05 19:21:36 +0000"
    },
    "done": true
  },
  "minecraft:recipes/building_blocks/nether_wart_block": {
    "criteria": {
      "has_nether_wart": "2021-09-05 19:16:25 +0000"
    },
    "done": true
  },
  "minecraft:recipes/food/cooked_porkchop_from_smoking": {
    "criteria": {
      "has_porkchop": "2021-09-05 19:15:55 +0000"
    },
    "done": true
  },
  "minecraft:recipes/food/cooked_porkchop": {
    "criteria": {
      "has_porkchop": "2021-09-05 19:15:55 +0000"
    },
    "done": true
  },
  "minecraft:adventure/root": {
    "criteria": {
      "killed_something": "2021-09-05 19:15:54 +0000"
    },
    "done": true
  },
  "minecraft:recipes/transportation/jungle_boat": {
    "criteria": {
      "in_water": "2021-09-05 19:21:36 +0000"
    },
    "done": true
  },
  "minecraft:recipes/misc/iron_nugget_from_smelting": {
    "criteria": {
      "has_iron_hoe": "2021-09-05 19:21:18 +0000"
    },
    "done": true
  },
  "minecraft:recipes/misc/pumpkin_seeds": {
    "criteria": {
      "has_pumpkin": "2021-09-05 19:18:16 +0000"
    },
    "done": true
  },
  "minecraft:recipes/transportation/spruce_boat": {
    "criteria": {
      "in_water": "2021-09-05 19:21:36 +0000"
    },
    "done": true
  },
  "minecraft:recipes/misc/gold_nugget_from_blasting": {
    "criteria": {
      "has_golden_axe": "2021-09-05 19:17:34 +0000"
    },
    "done": true
  },
  "DataVersion": 2586
}