{"stats":{"minecraft:killed":{"minecraft:pig":5,"minecraft:chicken":1},"minecraft:custom":{"minecraft:time_since_rest":1028,"minecraft:crouch_one_cm":15,"minecraft:walk_one_cm":8153,"minecraft:play_time":5606,"minecraft:sprint_one_cm":12410,"minecraft:open_enderchest":1,"minecraft:damage_taken":1405,"minecraft:deaths":1,"minecraft:sneak_time":153,"minecraft:mob_kills":6,"minecraft:jump":39,"minecraft:damage_dealt":540,"minecraft:leave_game":1,"minecraft:time_since_death":1022,"minecraft:total_world_time":5606,"minecraft:fall_one_cm":12950,"minecraft:fly_one_cm":3324},"minecraft:picked_up":{"minecraft:chicken":1,"minecraft:porkchop":11,"minecraft:emerald":6,"minecraft:egg":1},"minecraft:used":{"minecraft:stone_sword":15,"minecraft:written_book":5,"minecraft:leather_helmet":1}},"DataVersion":2730}