{"stats":{"minecraft:custom":{"minecraft:jump":11,"minecraft:time_since_rest":890,"minecraft:damage_dealt":200,"minecraft:leave_game":1,"minecraft:sprint_one_cm":3211,"minecraft:play_time":890,"minecraft:time_since_death":890,"minecraft:walk_one_cm":2794,"minecraft:total_world_time":890,"minecraft:mob_kills":2,"minecraft:fly_one_cm":1971},"minecraft:picked_up":{"minecraft:porkchop":4},"minecraft:used":{"minecraft:leather_helmet":1,"minecraft:stone_sword":4},"minecraft:killed":{"minecraft:pig":2}},"DataVersion":2730}