{"stats":{"minecraft:custom":{"minecraft:time_since_rest":9182,"minecraft:crouch_one_cm":596,"minecraft:play_time":9182,"minecraft:sprint_one_cm":9892,"minecraft:damage_taken":272,"minecraft:walk_one_cm":32606,"minecraft:sneak_time":148,"minecraft:mob_kills":40,"minecraft:interact_with_lectern":1,"minecraft:jump":135,"minecraft:damage_dealt":1803,"minecraft:leave_game":2,"minecraft:walk_on_water_one_cm":1627,"minecraft:time_since_death":9182,"minecraft:climb_one_cm":1498,"minecraft:total_world_time":9182,"minecraft:fly_one_cm":6872},"minecraft:picked_up":{"minecraft:feather":39,"minecraft:chicken":32,"minecraft:sweet_berries":21,"minecraft:porkchop":13,"minecraft:emerald":33,"minecraft:egg":32},"minecraft:used":{"minecraft:stone_sword":50,"minecraft:bow":2,"minecraft:sweet_berries":8},"minecraft:killed":{"minecraft:pig":7,"minecraft:chicken":32}},"DataVersion":2730}