{"stats":{"minecraft:custom":{"minecraft:jump":161,"minecraft:time_since_rest":4163,"minecraft:leave_game":1,"minecraft:damage_dealt":1890,"minecraft:damage_taken":8,"minecraft:sprint_one_cm":9325,"minecraft:play_time":4163,"minecraft:walk_on_water_one_cm":234,"minecraft:time_since_death":4163,"minecraft:walk_one_cm":15563,"minecraft:total_world_time":4163,"minecraft:mob_kills":19,"minecraft:fly_one_cm":14233},"minecraft:picked_up":{"minecraft:porkchop":31,"minecraft:emerald":1},"minecraft:used":{"minecraft:baked_potato":1,"minecraft:leather_helmet":1,"minecraft:stone_sword":38},"minecraft:killed":{"minecraft:pig":19}},"DataVersion":2730}