{"stats":{"minecraft:used":{"minecraft:iron_hoe":37,"minecraft:stone_sword":29,"minecraft:iron_axe":5,"minecraft:baked_potato":16,"minecraft:wooden_pickaxe":1,"minecraft:leather_helmet":2,"minecraft:leather_chestplate":1,"minecraft:chainmail_helmet":1,"minecraft:diamond_axe":5,"minecraft:stone_hoe":64,"minecraft:rotten_flesh":8,"minecraft:golden_hoe":92,"minecraft:wooden_sword":156,"minecraft:bow":5,"minecraft:sweet_berries":1,"minecraft:porkchop":1,"minecraft:cooked_porkchop":27,"minecraft:crossbow":153,"minecraft:golden_axe":542},"minecraft:custom":{"minecraft:time_since_rest":36871,"minecraft:open_enderchest":31,"minecraft:sprint_one_cm":452358,"minecraft:damage_taken":5460,"minecraft:walk_one_cm":221655,"minecraft:mob_kills":254,"minecraft:damage_dealt":34343,"minecraft:interact_with_crafting_table":1,"minecraft:tune_noteblock":1,"minecraft:fly_one_cm":240293,"minecraft:crouch_one_cm":46150,"minecraft:play_time":85693,"minecraft:deaths":4,"minecraft:sneak_time":7202,"minecraft:walk_under_water_one_cm":230,"minecraft:jump":1222,"minecraft:leave_game":1,"minecraft:walk_on_water_one_cm":5512,"minecraft:time_since_death":36868,"minecraft:total_world_time":85693,"minecraft:climb_one_cm":5088},"minecraft:killed":{"minecraft:sheep":29,"minecraft:skeleton":45,"minecraft:zombie":18,"minecraft:pig":114,"minecraft:chicken":45},"minecraft:picked_up":{"minecraft:feather":38,"minecraft:chicken":44,"minecraft:cooked_porkchop":2,"minecraft:sweet_berries":65,"minecraft:brown_wool":1,"minecraft:porkchop":229,"minecraft:redstone":1,"minecraft:rotten_flesh":25,"minecraft:cactus":46,"minecraft:arrow":64,"minecraft:bone":52,"minecraft:gray_wool":1,"minecraft:emerald":287,"minecraft:light_gray_wool":1,"minecraft:black_wool":1,"minecraft:sugar_cane":42,"minecraft:mutton":40,"minecraft:white_wool":25,"minecraft:egg":55},"minecraft:mined":{"minecraft:cactus":38,"minecraft:red_stained_glass":1},"minecraft:killed_by":{"minecraft:skeleton":2,"minecraft:zombie":2}},"DataVersion":2730}