{"stats":{"minecraft:killed":{"minecraft:pig":7,"minecraft:chicken":6},"minecraft:used":{"minecraft:iron_chestplate":1,"minecraft:stone_sword":4,"minecraft:iron_sword":8},"minecraft:custom":{"minecraft:time_since_rest":2569,"minecraft:crouch_one_cm":245,"minecraft:open_enderchest":1,"minecraft:play_time":2569,"minecraft:sprint_one_cm":10195,"minecraft:walk_one_cm":4257,"minecraft:sneak_time":69,"minecraft:mob_kills":13,"minecraft:jump":46,"minecraft:damage_dealt":890,"minecraft:leave_game":1,"minecraft:time_since_death":2569,"minecraft:total_world_time":2569,"minecraft:fly_one_cm":9133},"minecraft:picked_up":{"minecraft:feather":8,"minecraft:chicken":5,"minecraft:cooked_porkchop":11,"minecraft:porkchop":2,"minecraft:cooked_chicken":1,"minecraft:emerald":13,"minecraft:egg":6}},"DataVersion":2730}