{"stats":{"minecraft:killed_by":{"minecraft:skeleton":1},"minecraft:used":{"minecraft:stone_sword":14},"minecraft:custom":{"minecraft:time_since_rest":1314,"minecraft:deaths":1,"minecraft:crouch_one_cm":556,"minecraft:play_time":3878,"minecraft:sprint_one_cm":20856,"minecraft:damage_taken":370,"minecraft:walk_one_cm":9101,"minecraft:sneak_time":147,"minecraft:walk_under_water_one_cm":43,"minecraft:mob_kills":3,"minecraft:jump":84,"minecraft:damage_dealt":530,"minecraft:leave_game":1,"minecraft:time_since_death":1308,"minecraft:walk_on_water_one_cm":463,"minecraft:total_world_time":3878,"minecraft:fly_one_cm":17006},"minecraft:picked_up":{"minecraft:arrow":2,"minecraft:bone":2,"minecraft:chicken":1,"minecraft:porkchop":1,"minecraft:emerald":1,"minecraft:egg":1},"minecraft:killed":{"minecraft:skeleton":1,"minecraft:pig":1,"minecraft:chicken":1}},"DataVersion":2730}