{"stats":{"minecraft:picked_up":{"minecraft:porkchop":6},"minecraft:custom":{"minecraft:jump":14,"minecraft:time_since_rest":1419,"minecraft:damage_dealt":260,"minecraft:play_time":1419,"minecraft:leave_game":2,"minecraft:sprint_one_cm":9046,"minecraft:damage_taken":40,"minecraft:time_since_death":1419,"minecraft:walk_one_cm":2165,"minecraft:total_world_time":1419,"minecraft:mob_kills":3,"minecraft:fly_one_cm":2044},"minecraft:killed":{"minecraft:pig":3},"minecraft:used":{"minecraft:stone_sword":6}},"DataVersion":2730}