{"stats":{"minecraft:killed":{"minecraft:pig":64,"minecraft:chicken":70},"minecraft:picked_up":{"minecraft:feather":125,"minecraft:chicken":118,"minecraft:porkchop":185,"minecraft:emerald":165,"minecraft:egg":66},"minecraft:custom":{"minecraft:time_since_rest":13266,"minecraft:play_time":13266,"minecraft:sprint_one_cm":114901,"minecraft:damage_taken":36,"minecraft:walk_one_cm":29721,"minecraft:sneak_time":27,"minecraft:mob_kills":134,"minecraft:jump":340,"minecraft:damage_dealt":9020,"minecraft:leave_game":1,"minecraft:time_since_death":13266,"minecraft:walk_on_water_one_cm":4319,"minecraft:total_world_time":13266,"minecraft:fly_one_cm":83157},"minecraft:used":{"minecraft:stone_sword":17,"minecraft:iron_axe":110,"minecraft:baked_potato":3,"minecraft:leather_helmet":1,"minecraft:diamond_axe":22}},"DataVersion":2730}