{"stats":{"minecraft:used":{"minecraft:stone_sword":152,"minecraft:bow":4,"minecraft:baked_potato":2,"minecraft:crossbow":20},"minecraft:custom":{"minecraft:time_since_rest":10023,"minecraft:crouch_one_cm":317,"minecraft:open_enderchest":4,"minecraft:play_time":10023,"minecraft:sprint_one_cm":41727,"minecraft:damage_taken":110,"minecraft:walk_one_cm":40654,"minecraft:sneak_time":176,"minecraft:mob_kills":71,"minecraft:jump":86,"minecraft:damage_dealt":2940,"minecraft:leave_game":1,"minecraft:time_since_death":10023,"minecraft:walk_on_water_one_cm":2305,"minecraft:total_world_time":10023,"minecraft:interact_with_crafting_table":1,"minecraft:fly_one_cm":9237},"minecraft:picked_up":{"minecraft:feather":52,"minecraft:chicken":55,"minecraft:cooked_porkchop":1,"minecraft:sweet_berries":4,"minecraft:porkchop":30,"minecraft:emerald":58,"minecraft:egg":56},"minecraft:killed":{"minecraft:pig":17,"minecraft:chicken":53}},"DataVersion":2730}