{"stats":{"minecraft:used":{"minecraft:leather_helmet":1,"minecraft:stone_sword":5},"minecraft:custom":{"minecraft:jump":18,"minecraft:time_since_rest":1622,"minecraft:leave_game":1,"minecraft:open_enderchest":1,"minecraft:damage_dealt":194,"minecraft:sprint_one_cm":4602,"minecraft:play_time":1622,"minecraft:time_since_death":1622,"minecraft:walk_one_cm":6916,"minecraft:total_world_time":1622,"minecraft:mob_kills":2,"minecraft:fly_one_cm":2596},"minecraft:killed":{"minecraft:chicken":2},"minecraft:picked_up":{"minecraft:porkchop":2,"minecraft:feather":1,"minecraft:emerald":4,"minecraft:chicken":2,"minecraft:egg":2}},"DataVersion":2730}