{"stats":{"minecraft:killed":{"minecraft:skeleton":4,"minecraft:pig":4},"minecraft:used":{"minecraft:stone_sword":17,"minecraft:bow":15,"minecraft:baked_potato":9},"minecraft:custom":{"minecraft:time_since_rest":10483,"minecraft:crouch_one_cm":405,"minecraft:play_time":10483,"minecraft:sprint_one_cm":18886,"minecraft:open_enderchest":2,"minecraft:damage_taken":585,"minecraft:walk_one_cm":67684,"minecraft:sneak_time":64,"minecraft:interact_with_anvil":1,"minecraft:mob_kills":9,"minecraft:jump":192,"minecraft:interact_with_grindstone":1,"minecraft:damage_dealt":402,"minecraft:leave_game":1,"minecraft:time_since_death":10483,"minecraft:walk_on_water_one_cm":215,"minecraft:total_world_time":10483,"minecraft:climb_one_cm":549,"minecraft:fly_one_cm":18189},"minecraft:picked_up":{"minecraft:bone":9,"minecraft:arrow":13,"minecraft:porkchop":5,"minecraft:emerald":5}},"DataVersion":2730}