{"stats":{"minecraft:killed":{"minecraft:pig":25,"minecraft:chicken":6},"minecraft:custom":{"minecraft:time_since_rest":13898,"minecraft:crouch_one_cm":22082,"minecraft:play_time":13898,"minecraft:sprint_one_cm":4888,"minecraft:damage_taken":130,"minecraft:walk_one_cm":47221,"minecraft:sneak_time":1455,"minecraft:mob_kills":31,"minecraft:jump":168,"minecraft:damage_dealt":2440,"minecraft:leave_game":1,"minecraft:time_since_death":13898,"minecraft:walk_on_water_one_cm":569,"minecraft:climb_one_cm":1225,"minecraft:total_world_time":13898,"minecraft:fly_one_cm":21592},"minecraft:picked_up":{"minecraft:feather":6,"minecraft:chicken":7,"minecraft:cooked_porkchop":15,"minecraft:sweet_berries":4,"minecraft:porkchop":62,"minecraft:emerald":34,"minecraft:sugar_cane":26,"minecraft:egg":7},"minecraft:used":{"minecraft:stone_hoe":70,"minecraft:iron_hoe":39,"minecraft:stone_sword":22,"minecraft:bow":2,"minecraft:iron_axe":12,"minecraft:baked_potato":1,"minecraft:iron_sword":9}},"DataVersion":2730}