{"stats":{"minecraft:custom":{"minecraft:jump":22,"minecraft:time_since_rest":77,"minecraft:leave_game":1,"minecraft:crouch_one_cm":84,"minecraft:deaths":5,"minecraft:damage_taken":1450,"minecraft:sprint_one_cm":11043,"minecraft:play_time":2638,"minecraft:time_since_death":76,"minecraft:walk_one_cm":3847,"minecraft:sneak_time":27,"minecraft:total_world_time":2638,"minecraft:interact_with_lectern":1,"minecraft:fly_one_cm":34073},"minecraft:used":{"minecraft:baked_potato":3,"minecraft:leather_helmet":1,"minecraft:written_book":2},"minecraft:killed_by":{"minecraft:blaze":3}},"DataVersion":2730}