{"stats":{"minecraft:used":{"minecraft:writable_book":2,"minecraft:stone_sword":295,"minecraft:iron_shovel":1057,"minecraft:stripped_warped_stem":66,"minecraft:shield":54,"minecraft:iron_sword":457,"minecraft:stone":1,"minecraft:player_head":1,"minecraft:stone_hoe":1311,"minecraft:rotten_flesh":2,"minecraft:torch":7,"minecraft:warped_wart_block":270,"minecraft:golden_shovel":226,"minecraft:honey_bottle":2,"minecraft:iron_hoe":137,"minecraft:sea_lantern":5,"minecraft:iron_axe":77,"minecraft:totem_of_undying":2,"minecraft:stone_brick_stairs":1,"minecraft:golden_sword":4,"minecraft:golden_carrot":14,"minecraft:bow":50,"minecraft:written_book":4,"minecraft:sweet_berries":4,"minecraft:enchanted_golden_apple":8,"minecraft:golden_axe":2864,"minecraft:end_stone_bricks":76,"minecraft:warped_fungus_on_a_stick":13,"minecraft:stone_pickaxe":15,"minecraft:baked_potato":29,"minecraft:ender_pearl":5,"minecraft:diamond_axe":286,"minecraft:sugar_cane":2,"minecraft:leather_boots":1,"minecraft:golden_hoe":566,"minecraft:comparator":3,"minecraft:crossbow":1,"minecraft:cod":1,"minecraft:end_stone":53,"minecraft:hoglin_spawn_egg":1,"minecraft:lever":1,"minecraft:diamond_pickaxe":726,"minecraft:black_concrete":5,"minecraft:birch_slab":31,"minecraft:oak_button":8,"minecraft:iron_pickaxe":26,"minecraft:oak_pressure_plate":2,"minecraft:stone_axe":56,"minecraft:diamond_sword":45,"minecraft:wooden_sword":7,"minecraft:porkchop":14,"minecraft:cooked_porkchop":383,"minecraft:smooth_stone_slab":1,"minecraft:pumpkin_pie":7,"minecraft:splash_potion":272,"minecraft:golden_pickaxe":150,"minecraft:experience_bottle":4},"minecraft:crafted":{"minecraft:golden_carrot":36,"minecraft:leather_boots":1,"minecraft:player_head":2,"minecraft:blaze_powder":2166,"minecraft:enchanted_golden_apple":8,"minecraft:diamond_block":1,"minecraft:diamond":23,"minecraft:diamond_leggings":1,"minecraft:bow":1,"minecraft:iron_axe":2,"minecraft:iron_hoe":1,"minecraft:stone_hoe":1,"minecraft:ender_eye":64,"minecraft:ghast_tear":23,"minecraft:golden_axe":1,"minecraft:firework_star":1,"minecraft:diamond_sword":2,"minecraft:arrow":1988,"minecraft:emerald":134,"minecraft:cooked_porkchop":180,"minecraft:chainmail_chestplate":1,"minecraft:golden_pickaxe":1,"minecraft:enchanted_book":1,"minecraft:air":0,"minecraft:diamond_pickaxe":1,"minecraft:shield":1,"minecraft:stone_sword":2,"minecraft:iron_leggings":1,"minecraft:shears":1,"minecraft:diamond_chestplate":1},"minecraft:custom":{"minecraft:mob_kills":1260,"minecraft:interact_with_anvil":28,"minecraft:interact_with_crafting_table":14,"minecraft:open_barrel":3,"minecraft:damage_dealt_resisted":72840,"minecraft:leave_game":61,"minecraft:time_since_death":9106,"minecraft:climb_one_cm":68979,"minecraft:damage_resisted":277883,"minecraft:sprint_one_cm":2133984,"minecraft:walk_one_cm":4561571,"minecraft:damage_blocked_by_shield":24326,"minecraft:drop":540,"minecraft:damage_dealt_absorbed":12150,"minecraft:talked_to_villager":196,"minecraft:target_hit":4,"minecraft:play_time":1098040,"minecraft:deaths":185,"minecraft:sneak_time":213834,"minecraft:walk_under_water_one_cm":15758,"minecraft:boat_one_cm":2188,"minecraft:interact_with_lectern":1,"minecraft:jump":12933,"minecraft:interact_with_blast_furnace":2,"minecraft:walk_on_water_one_cm":40523,"minecraft:total_world_time":249597,"minecraft:traded_with_villager":493,"minecraft:time_since_rest":9107,"minecraft:open_enderchest":152,"minecraft:damage_taken":4013293,"minecraft:damage_absorbed":3260,"minecraft:damage_dealt":1912085,"minecraft:swim_one_cm":2804,"minecraft:fly_one_cm":6332063,"minecraft:open_chest":33,"minecraft:crouch_one_cm":3514597,"minecraft:fall_one_cm":2601195},"minecraft:dropped":{"minecraft:enchanted_book":9,"minecraft:stone_hoe":5,"minecraft:iron_ingot":4,"minecraft:porkchop":14,"minecraft:iron_sword":6,"minecraft:gray_stained_glass_pane":21,"minecraft:diamond_axe":1,"minecraft:oak_pressure_plate":1,"minecraft:warped_fungus":2,"minecraft:glass_bottle":3,"minecraft:ender_pearl":202,"minecraft:golden_pickaxe":3,"minecraft:purple_glazed_terracotta":19,"minecraft:diamond":64,"minecraft:cooked_porkchop":25,"minecraft:diamond_leggings":1,"minecraft:feather":6,"minecraft:warped_fungus_on_a_stick":9,"minecraft:crossbow":2,"minecraft:golden_axe":4,"minecraft:leather_helmet":10,"minecraft:coal":26,"minecraft:birch_slab":3,"minecraft:item_frame":2,"minecraft:red_carpet":2,"minecraft:end_rod":7,"minecraft:emerald":257,"minecraft:gold_block":1,"minecraft:packed_ice":16,"minecraft:ice":133,"minecraft:golden_carrot":22,"minecraft:netherite_boots":4,"minecraft:iron_leggings":1,"minecraft:pumpkin":20,"minecraft:oak_stairs":1,"minecraft:gold_nugget":1,"minecraft:golden_hoe":1,"minecraft:iron_axe":3,"minecraft:black_concrete":65,"minecraft:iron_pickaxe":6,"minecraft:cactus":235,"minecraft:paper":1,"minecraft:iron_shovel":4,"minecraft:string":4,"minecraft:end_crystal":12,"minecraft:bone":65,"minecraft:stone_axe":1,"minecraft:sweet_berries":1,"minecraft:nether_wart":30,"minecraft:sugar_cane":25,"minecraft:player_head":29,"minecraft:stone_sword":8,"minecraft:golden_chestplate":1,"minecraft:blaze_rod":142,"minecraft:experience_bottle":15,"minecraft:chicken":5,"minecraft:rotten_flesh":39,"minecraft:iron_hoe":2,"minecraft:end_stone":14,"minecraft:blaze_powder":128,"minecraft:honey_bottle":16,"minecraft:nether_bricks":1,"minecraft:totem_of_undying":9,"minecraft:shears":3,"minecraft:chainmail_chestplate":1,"minecraft:poppy":1,"minecraft:diamond_sword":14,"minecraft:leather_chestplate":9,"minecraft:turtle_helmet":2,"minecraft:stone":1,"minecraft:shield":1,"minecraft:oak_button":120,"minecraft:diamond_chestplate":3,"minecraft:diamond_pickaxe":1,"minecraft:cake":1,"minecraft:mossy_stone_bricks":1,"minecraft:blue_ice":81,"minecraft:leather_boots":27,"minecraft:golden_leggings":2,"minecraft:end_portal_frame":4,"minecraft:leather_leggings":20,"minecraft:stone_pressure_plate":1,"minecraft:stone_bricks":1,"minecraft:iron_ore":1,"minecraft:arrow":255,"minecraft:end_stone_bricks":1,"minecraft:bow":6,"minecraft:stone_pickaxe":1,"minecraft:warped_wart_block":1,"minecraft:magma_cream":37,"minecraft:ghast_tear":35,"minecraft:stone_brick_stairs":1,"minecraft:splash_potion":1,"minecraft:egg":1},"minecraft:killed":{"minecraft:evoker":7,"minecraft:cave_spider":2,"minecraft:zombified_piglin":5,"minecraft:giant":55,"minecraft:spider":2,"minecraft:endermite":5,"minecraft:zoglin":56,"minecraft:phantom":2,"minecraft:skeleton":93,"minecraft:chicken":68,"minecraft:drowned":1,"minecraft:illusioner":27,"minecraft:piglin_brute":12,"minecraft:magma_cube":2,"minecraft:pig":413,"minecraft:husk":12,"minecraft:iron_golem":1,"minecraft:ravager":10,"minecraft:hoglin":1,"minecraft:sheep":7,"minecraft:pillager":4,"minecraft:zombie":51,"minecraft:wither_skeleton":75,"minecraft:blaze":240,"minecraft:enderman":81},"minecraft:picked_up":{"minecraft:iron_chestplate":2,"minecraft:chicken":148,"minecraft:nether_wart":1519,"minecraft:leather_leggings":29,"minecraft:golden_pickaxe":1,"minecraft:turtle_helmet":2,"minecraft:packed_ice":291,"minecraft:diamond_sword":12,"minecraft:gold_block":1,"minecraft:enchanted_book":18,"minecraft:golden_shovel":2,"minecraft:golden_sword":4,"minecraft:string":5,"minecraft:wooden_sword":1,"minecraft:smooth_stone_slab":1,"minecraft:iron_leggings":2,"minecraft:netherite_scrap":1,"minecraft:item_frame":2,"minecraft:iron_shovel":6,"minecraft:gold_nugget":19,"minecraft:stripped_warped_stem":50,"minecraft:player_head":34,"minecraft:poppy":1,"minecraft:iron_pickaxe":10,"minecraft:sugar_cane":228,"minecraft:phantom_membrane":1,"minecraft:iron_boots":3,"minecraft:egg":90,"minecraft:end_stone":143,"minecraft:torch":1,"minecraft:fire_charge":32,"minecraft:porkchop":1045,"minecraft:golden_axe":2,"minecraft:brown_dye":1,"minecraft:stone_pressure_plate":1,"minecraft:rotten_flesh":406,"minecraft:arrow":173,"minecraft:stone_sword":10,"minecraft:cactus":174,"minecraft:honey_bottle":4,"minecraft:diamond_chestplate":2,"minecraft:golden_hoe":1,"minecraft:diamond_boots":1,"minecraft:end_rod":7,"minecraft:gold_ingot":13,"minecraft:totem_of_undying":15,"minecraft:blaze_rod":796,"minecraft:mutton":6,"minecraft:cod":1,"minecraft:white_wool":4,"minecraft:netherite_boots":5,"minecraft:leather_chestplate":9,"minecraft:feather":120,"minecraft:magma_cream":3,"minecraft:warped_fungus_on_a_stick":10,"minecraft:brown_wool":1,"minecraft:golden_leggings":1,"minecraft:red_mushroom_block":1,"minecraft:end_portal_frame":4,"minecraft:ice":206,"minecraft:chainmail_chestplate":1,"minecraft:paper":1,"minecraft:leather_boots":29,"minecraft:red_carpet":2,"minecraft:bone":228,"minecraft:stone_bricks":1,"minecraft:bow":11,"minecraft:iron_ingot":4,"minecraft:glass_bottle":2,"minecraft:iron_sword":11,"minecraft:stone_hoe":1,"minecraft:ghast_tear":11,"minecraft:warped_fungus":2,"minecraft:cooked_porkchop":46,"minecraft:pumpkin":1361,"minecraft:sweet_berries":78,"minecraft:quartz":64,"minecraft:warped_wart_block":1,"minecraft:spider_eye":4,"minecraft:leather_helmet":11,"minecraft:iron_hoe":1,"minecraft:diamond":113,"minecraft:purple_glazed_terracotta":356,"minecraft:iron_helmet":1,"minecraft:crossbow":2,"minecraft:blue_ice":347,"minecraft:emerald":813,"minecraft:oak_button":60,"minecraft:coal":65,"minecraft:ender_pearl":319,"minecraft:sunflower":1},"minecraft:mined":{"minecraft:stripped_warped_stem":56,"minecraft:red_carpet":1,"minecraft:end_stone":149,"minecraft:nether_wart":1315,"minecraft:pumpkin":1403,"minecraft:gold_block":1,"minecraft:vine":1,"minecraft:packed_ice":309,"minecraft:soul_sand":1,"minecraft:sugar_cane":148,"minecraft:cactus":133,"minecraft:blue_ice":265,"minecraft:ice":170,"minecraft:smooth_stone_slab":1,"minecraft:grass":1,"minecraft:coal_ore":15,"minecraft:stone_bricks":1},"minecraft:killed_by":{"minecraft:husk":17,"minecraft:wither_skeleton":2,"minecraft:enderman":8,"minecraft:ravager":3,"minecraft:cave_spider":2,"minecraft:blaze":5,"minecraft:zombie":7,"minecraft:illusioner":2,"minecraft:endermite":3}},"DataVersion":2730}