{"stats":{"minecraft:killed_by":{"minecraft:zombie":1},"minecraft:used":{"minecraft:leather_helmet":1,"minecraft:stone_sword":23},"minecraft:custom":{"minecraft:jump":14,"minecraft:time_since_rest":416,"minecraft:damage_taken":330,"minecraft:walk_one_cm":7783,"minecraft:leave_game":2,"minecraft:damage_dealt":414,"minecraft:sprint_one_cm":6916,"minecraft:time_since_death":410,"minecraft:walk_on_water_one_cm":484,"minecraft:play_time":2490,"minecraft:deaths":1,"minecraft:total_world_time":2490,"minecraft:mob_kills":7,"minecraft:fly_one_cm":2160},"minecraft:picked_up":{"minecraft:feather":6,"minecraft:chicken":6,"minecraft:emerald":6,"minecraft:egg":6},"minecraft:killed":{"minecraft:chicken":6}},"DataVersion":2730}