{"stats":{"minecraft:picked_up":{"minecraft:brown_wool":1,"minecraft:gray_wool":2,"minecraft:emerald":42,"minecraft:light_gray_wool":2,"minecraft:mutton":66,"minecraft:white_wool":40},"minecraft:custom":{"minecraft:time_since_rest":6324,"minecraft:crouch_one_cm":2054,"minecraft:play_time":6324,"minecraft:sprint_one_cm":20568,"minecraft:damage_taken":13,"minecraft:walk_one_cm":19782,"minecraft:sneak_time":512,"minecraft:mob_kills":46,"minecraft:jump":286,"minecraft:damage_dealt":3663,"minecraft:leave_game":1,"minecraft:time_since_death":6324,"minecraft:walk_on_water_one_cm":572,"minecraft:total_world_time":6324,"minecraft:fly_one_cm":30655},"minecraft:used":{"minecraft:stone_sword":103,"minecraft:chainmail_chestplate":1,"minecraft:baked_potato":1},"minecraft:killed":{"minecraft:sheep":45}},"DataVersion":2730}