{"stats":{"minecraft:used":{"minecraft:stone_sword":10,"minecraft:bow":2,"minecraft:leather_helmet":1,"minecraft:golden_axe":211},"minecraft:custom":{"minecraft:time_since_rest":1880,"minecraft:deaths":1,"minecraft:play_time":8839,"minecraft:sprint_one_cm":30177,"minecraft:damage_taken":380,"minecraft:walk_one_cm":11440,"minecraft:sneak_time":5,"minecraft:mob_kills":9,"minecraft:jump":143,"minecraft:damage_dealt":546,"minecraft:leave_game":3,"minecraft:time_since_death":1879,"minecraft:total_world_time":8839,"minecraft:fly_one_cm":24996},"minecraft:killed":{"minecraft:sheep":1,"minecraft:pig":3,"minecraft:chicken":4},"minecraft:picked_up":{"minecraft:feather":3,"minecraft:chicken":4,"minecraft:sweet_berries":42,"minecraft:porkchop":8,"minecraft:emerald":5,"minecraft:egg":4}},"DataVersion":2730}