{"stats":{"minecraft:killed":{"minecraft:pig":18,"minecraft:chicken":11},"minecraft:custom":{"minecraft:time_since_rest":4848,"minecraft:play_time":4848,"minecraft:sprint_one_cm":30017,"minecraft:walk_one_cm":10202,"minecraft:mob_kills":29,"minecraft:jump":121,"minecraft:damage_dealt":2200,"minecraft:leave_game":2,"minecraft:time_since_death":4848,"minecraft:walk_on_water_one_cm":278,"minecraft:total_world_time":4848,"minecraft:fall_one_cm":2208,"minecraft:fly_one_cm":27151},"minecraft:used":{"minecraft:stone_sword":10,"minecraft:bow":1,"minecraft:iron_sword":22},"minecraft:picked_up":{"minecraft:feather":12,"minecraft:chicken":9,"minecraft:cooked_porkchop":3,"minecraft:porkchop":34,"minecraft:cooked_chicken":2,"minecraft:emerald":28,"minecraft:egg":11}},"DataVersion":3700}