{"stats":{"minecraft:custom":{"minecraft:jump":32,"minecraft:time_since_rest":889,"minecraft:leave_game":1,"minecraft:damage_dealt":500,"minecraft:crouch_one_cm":21,"minecraft:sprint_one_cm":5243,"minecraft:play_time":889,"minecraft:open_enderchest":1,"minecraft:time_since_death":889,"minecraft:walk_one_cm":5704,"minecraft:sneak_time":1,"minecraft:bell_ring":1,"minecraft:total_world_time":889,"minecraft:mob_kills":11,"minecraft:fly_one_cm":5530,"minecraft:interact_with_lectern":1},"minecraft:picked_up":{"minecraft:porkchop":5,"minecraft:emerald":10,"minecraft:feather":11,"minecraft:chicken":8,"minecraft:egg":8},"minecraft:used":{"minecraft:stone_sword":14},"minecraft:killed":{"minecraft:pig":2,"minecraft:chicken":9}},"DataVersion":2730}