{"stats":{"minecraft:used":{"minecraft:stone_hoe":70,"minecraft:iron_hoe":40,"minecraft:golden_hoe":117,"minecraft:stone_sword":27,"minecraft:bow":1,"minecraft:written_book":3,"minecraft:iron_axe":48,"minecraft:stone_shovel":13,"minecraft:golden_axe":211},"minecraft:custom":{"minecraft:time_since_rest":722,"minecraft:crouch_one_cm":65223,"minecraft:deaths":2,"minecraft:sprint_one_cm":11012,"minecraft:play_time":37773,"minecraft:damage_taken":605,"minecraft:walk_one_cm":128716,"minecraft:trigger_trapped_chest":3,"minecraft:sneak_time":4270,"minecraft:walk_under_water_one_cm":1726,"minecraft:mob_kills":59,"minecraft:jump":352,"minecraft:damage_dealt":3826,"minecraft:leave_game":2,"minecraft:walk_on_water_one_cm":5407,"minecraft:time_since_death":720,"minecraft:climb_one_cm":1658,"minecraft:total_world_time":37773,"minecraft:swim_one_cm":9337,"minecraft:fall_one_cm":1679,"minecraft:interact_with_crafting_table":2,"minecraft:fly_one_cm":85983},"minecraft:killed":{"minecraft:pig":25,"minecraft:chicken":33},"minecraft:picked_up":{"minecraft:feather":61,"minecraft:chicken":66,"minecraft:porkchop":80,"minecraft:emerald":96,"minecraft:sugar_cane":36,"minecraft:egg":34}},"DataVersion":2730}