{"stats":{"minecraft:custom":{"minecraft:jump":43,"minecraft:time_since_rest":37,"minecraft:leave_game":1,"minecraft:deaths":1,"minecraft:damage_dealt":523,"minecraft:damage_taken":320,"minecraft:sprint_one_cm":5356,"minecraft:play_time":1156,"minecraft:time_since_death":35,"minecraft:walk_one_cm":5955,"minecraft:total_world_time":1156,"minecraft:mob_kills":1,"minecraft:fly_one_cm":11480},"minecraft:used":{"minecraft:leather_helmet":1,"minecraft:stone_sword":14},"minecraft:killed_by":{"minecraft:skeleton":1},"minecraft:killed":{"minecraft:skeleton":1}},"DataVersion":2730}