{"stats":{"minecraft:used":{"minecraft:stone_sword":5,"minecraft:bow":1},"minecraft:killed":{"minecraft:pig":2},"minecraft:picked_up":{"minecraft:porkchop":2},"minecraft:custom":{"minecraft:jump":23,"minecraft:time_since_rest":1014,"minecraft:damage_dealt":244,"minecraft:crouch_one_cm":20,"minecraft:leave_game":1,"minecraft:sprint_one_cm":4774,"minecraft:play_time":1014,"minecraft:open_enderchest":1,"minecraft:time_since_death":1014,"minecraft:walk_one_cm":2468,"minecraft:sneak_time":12,"minecraft:total_world_time":1014,"minecraft:mob_kills":2,"minecraft:fly_one_cm":4979}},"DataVersion":2730}