{"stats":{"minecraft:used":{"minecraft:golden_carrot":2,"minecraft:stone_sword":49,"minecraft:bow":5,"minecraft:iron_axe":27,"minecraft:baked_potato":14},"minecraft:custom":{"minecraft:time_since_rest":20405,"minecraft:open_enderchest":1,"minecraft:deaths":1,"minecraft:crouch_one_cm":268,"minecraft:sprint_one_cm":110768,"minecraft:play_time":37608,"minecraft:damage_taken":1370,"minecraft:walk_one_cm":117461,"minecraft:sneak_time":116,"minecraft:walk_under_water_one_cm":1540,"minecraft:mob_kills":63,"minecraft:jump":771,"minecraft:damage_dealt":2680,"minecraft:leave_game":2,"minecraft:time_since_death":20404,"minecraft:walk_on_water_one_cm":4765,"minecraft:climb_one_cm":209,"minecraft:total_world_time":37608,"minecraft:swim_one_cm":6545,"minecraft:fly_one_cm":135911},"minecraft:picked_up":{"minecraft:cactus":139,"minecraft:feather":88,"minecraft:chicken":85,"minecraft:porkchop":8,"minecraft:emerald":70,"minecraft:mutton":3,"minecraft:white_wool":1,"minecraft:egg":56},"minecraft:killed":{"minecraft:sheep":1,"minecraft:pig":4,"minecraft:chicken":58},"minecraft:mined":{"minecraft:cyan_stained_glass_pane":4,"minecraft:cactus":142,"minecraft:cyan_stained_glass":35}},"DataVersion":2730}