{"stats":{"minecraft:custom":{"minecraft:jump":35,"minecraft:time_since_rest":2604,"minecraft:leave_game":1,"minecraft:damage_dealt":170,"minecraft:walk_on_water_one_cm":1159,"minecraft:sprint_one_cm":1571,"minecraft:open_enderchest":1,"minecraft:play_time":2604,"minecraft:damage_taken":10,"minecraft:time_since_death":2604,"minecraft:walk_one_cm":27219,"minecraft:total_world_time":2604,"minecraft:mob_kills":2,"minecraft:fly_one_cm":4941,"minecraft:interact_with_lectern":3},"minecraft:picked_up":{"minecraft:porkchop":23,"minecraft:emerald":2},"minecraft:used":{"minecraft:stone_sword":5,"minecraft:bow":1},"minecraft:killed":{"minecraft:pig":2}},"DataVersion":2730}