{"stats":{"minecraft:picked_up":{"minecraft:porkchop":11,"minecraft:feather":20,"minecraft:chicken":19,"minecraft:emerald":20,"minecraft:egg":18},"minecraft:custom":{"minecraft:jump":54,"minecraft:time_since_rest":6030,"minecraft:damage_dealt":1300,"minecraft:crouch_one_cm":113,"minecraft:damage_taken":40,"minecraft:sprint_one_cm":20928,"minecraft:play_time":6030,"minecraft:walk_on_water_one_cm":780,"minecraft:time_since_death":6030,"minecraft:walk_one_cm":18615,"minecraft:sneak_time":22,"minecraft:total_world_time":6030,"minecraft:mob_kills":27,"minecraft:fly_one_cm":10440,"minecraft:leave_game":1},"minecraft:used":{"minecraft:stone_sword":27},"minecraft:killed":{"minecraft:pig":6,"minecraft:chicken":21}},"DataVersion":2730}