{"stats":{"minecraft:killed_by":{"minecraft:zombie":1},"minecraft:custom":{"minecraft:jump":34,"minecraft:open_chest":2,"minecraft:time_since_rest":1247,"minecraft:deaths":1,"minecraft:damage_dealt":45,"minecraft:play_one_minute":4286,"minecraft:damage_taken":310,"minecraft:leave_game":2,"minecraft:sprint_one_cm":8551,"minecraft:walk_on_water_one_cm":66,"minecraft:time_since_death":1227,"minecraft:walk_one_cm":6904,"minecraft:interact_with_crafting_table":1,"minecraft:fly_one_cm":4884,"minecraft:open_barrel":1}},"DataVersion":2586}