{"stats":{"minecraft:used":{"minecraft:iron_hoe":51,"minecraft:stone_sword":10,"minecraft:bow":2,"minecraft:written_book":1,"minecraft:cooked_porkchop":3,"minecraft:iron_sword":61},"minecraft:picked_up":{"minecraft:bone":4,"minecraft:arrow":4,"minecraft:feather":20,"minecraft:cooked_porkchop":56,"minecraft:sweet_berries":6,"minecraft:porkchop":3,"minecraft:cooked_chicken":22,"minecraft:emerald":17,"minecraft:sugar_cane":101,"minecraft:egg":13},"minecraft:mined":{"minecraft:sugar_cane":51},"minecraft:custom":{"minecraft:interact_with_anvil":1,"minecraft:time_since_rest":10764,"minecraft:crouch_one_cm":76,"minecraft:play_time":10764,"minecraft:sprint_one_cm":95728,"minecraft:open_enderchest":5,"minecraft:damage_taken":240,"minecraft:walk_one_cm":44474,"minecraft:sneak_time":16,"minecraft:walk_under_water_one_cm":1246,"minecraft:mob_kills":46,"minecraft:interact_with_lectern":1,"minecraft:jump":289,"minecraft:interact_with_grindstone":1,"minecraft:damage_dealt":3985,"minecraft:leave_game":1,"minecraft:time_since_death":10764,"minecraft:walk_on_water_one_cm":2476,"minecraft:climb_one_cm":1701,"minecraft:total_world_time":10764,"minecraft:swim_one_cm":1658,"minecraft:interact_with_crafting_table":1,"minecraft:target_hit":1,"minecraft:fly_one_cm":63525},"minecraft:killed":{"minecraft:skeleton":2,"minecraft:drowned":1,"minecraft:pig":28,"minecraft:chicken":14}},"DataVersion":2730}