{"stats":{"minecraft:used":{"minecraft:stone_sword":11},"minecraft:killed":{"minecraft:pig":4,"minecraft:chicken":1},"minecraft:custom":{"minecraft:jump":27,"minecraft:time_since_rest":843,"minecraft:damage_dealt":440,"minecraft:play_time":843,"minecraft:leave_game":2,"minecraft:sprint_one_cm":2014,"minecraft:walk_on_water_one_cm":215,"minecraft:time_since_death":843,"minecraft:walk_one_cm":2368,"minecraft:total_world_time":843,"minecraft:mob_kills":5,"minecraft:fly_one_cm":4453},"minecraft:picked_up":{"minecraft:porkchop":9,"minecraft:cooked_chicken":4,"minecraft:emerald":3,"minecraft:egg":1}},"DataVersion":2730}