{"stats":{"minecraft:used":{"minecraft:fishing_rod":11,"minecraft:stone_sword":9,"minecraft:cooked_porkchop":1,"minecraft:baked_potato":1,"minecraft:leather_helmet":1,"minecraft:iron_sword":11},"minecraft:custom":{"minecraft:time_since_rest":8453,"minecraft:crouch_one_cm":223,"minecraft:play_time":8453,"minecraft:sprint_one_cm":25464,"minecraft:damage_taken":130,"minecraft:walk_one_cm":22235,"minecraft:sneak_time":43,"minecraft:mob_kills":18,"minecraft:interact_with_lectern":1,"minecraft:jump":188,"minecraft:damage_dealt":1150,"minecraft:leave_game":13,"minecraft:walk_on_water_one_cm":383,"minecraft:time_since_death":8453,"minecraft:total_world_time":8006,"minecraft:fish_caught":1,"minecraft:fly_one_cm":39518},"minecraft:killed":{"minecraft:pig":8,"minecraft:chicken":10},"minecraft:picked_up":{"minecraft:feather":12,"minecraft:chicken":5,"minecraft:cooked_porkchop":14,"minecraft:sweet_berries":20,"minecraft:porkchop":8,"minecraft:cooked_chicken":6,"minecraft:emerald":9,"minecraft:cod":1,"minecraft:egg":10}},"DataVersion":2730}