{"stats":{"minecraft:killed":{"minecraft:skeleton":2,"minecraft:pig":8},"minecraft:used":{"minecraft:stone_hoe":55,"minecraft:iron_hoe":43,"minecraft:stone_sword":31,"minecraft:bow":3,"minecraft:baked_potato":2,"minecraft:leather_helmet":1},"minecraft:custom":{"minecraft:time_since_rest":4211,"minecraft:play_time":4211,"minecraft:sprint_one_cm":20246,"minecraft:damage_taken":370,"minecraft:walk_one_cm":7586,"minecraft:mob_kills":10,"minecraft:jump":73,"minecraft:damage_dealt":1343,"minecraft:leave_game":1,"minecraft:time_since_death":4211,"minecraft:walk_on_water_one_cm":1302,"minecraft:total_world_time":4211,"minecraft:fly_one_cm":8608},"minecraft:picked_up":{"minecraft:arrow":2,"minecraft:bone":2,"minecraft:porkchop":11,"minecraft:emerald":10,"minecraft:sugar_cane":37}},"DataVersion":2730}