{"stats":{"minecraft:used":{"minecraft:stone_sword":43,"minecraft:stone_hoe":56},"minecraft:custom":{"minecraft:jump":145,"minecraft:time_since_rest":6297,"minecraft:leave_game":1,"minecraft:damage_dealt":1129,"minecraft:damage_taken":167,"minecraft:sprint_one_cm":25532,"minecraft:play_time":6297,"minecraft:walk_on_water_one_cm":899,"minecraft:time_since_death":6297,"minecraft:walk_one_cm":17893,"minecraft:climb_one_cm":1407,"minecraft:total_world_time":6297,"minecraft:mob_kills":15,"minecraft:fly_one_cm":13400},"minecraft:killed":{"minecraft:pig":9,"minecraft:chicken":5},"minecraft:picked_up":{"minecraft:porkchop":20,"minecraft:feather":3,"minecraft:chicken":5,"minecraft:emerald":5,"minecraft:egg":6}},"DataVersion":2730}