{"stats":{"minecraft:custom":{"minecraft:jump":54,"minecraft:time_since_rest":2453,"minecraft:damage_dealt":761,"minecraft:leave_game":1,"minecraft:sprint_one_cm":10648,"minecraft:play_time":2453,"minecraft:damage_taken":100,"minecraft:time_since_death":2453,"minecraft:walk_one_cm":5941,"minecraft:total_world_time":2453,"minecraft:mob_kills":9,"minecraft:fly_one_cm":6055},"minecraft:picked_up":{"minecraft:porkchop":22,"minecraft:emerald":1},"minecraft:used":{"minecraft:stone_sword":20},"minecraft:killed":{"minecraft:pig":9}},"DataVersion":2730}