{"stats":{"minecraft:killed":{"minecraft:chicken":4},"minecraft:custom":{"minecraft:jump":40,"minecraft:time_since_rest":1583,"minecraft:walk_on_water_one_cm":580,"minecraft:damage_dealt":150,"minecraft:damage_taken":8,"minecraft:play_time":1583,"minecraft:leave_game":3,"minecraft:sprint_one_cm":6716,"minecraft:time_since_death":1583,"minecraft:walk_one_cm":5223,"minecraft:total_world_time":1583,"minecraft:mob_kills":4,"minecraft:fly_one_cm":11491},"minecraft:picked_up":{"minecraft:chicken":4,"minecraft:feather":3,"minecraft:emerald":7,"minecraft:egg":4},"minecraft:used":{"minecraft:leather_helmet":1,"minecraft:stone_sword":6}},"DataVersion":2730}