{"stats":{"minecraft:used":{"minecraft:leather_helmet":1,"minecraft:stone_sword":33},"minecraft:killed":{"minecraft:pig":4,"minecraft:chicken":23},"minecraft:custom":{"minecraft:jump":48,"minecraft:time_since_rest":2748,"minecraft:leave_game":1,"minecraft:damage_taken":20,"minecraft:damage_dealt":1250,"minecraft:sprint_one_cm":9552,"minecraft:play_time":2748,"minecraft:time_since_death":2748,"minecraft:walk_one_cm":7702,"minecraft:total_world_time":2748,"minecraft:mob_kills":27,"minecraft:fly_one_cm":4130},"minecraft:picked_up":{"minecraft:porkchop":4,"minecraft:emerald":23,"minecraft:feather":26,"minecraft:chicken":23,"minecraft:egg":23}},"DataVersion":2730}