{"stats":{"minecraft:used":{"minecraft:baked_potato":5,"minecraft:leather_helmet":1,"minecraft:stone_sword":2},"minecraft:custom":{"minecraft:jump":301,"minecraft:time_since_rest":1180,"minecraft:damage_taken":624,"minecraft:damage_dealt":115,"minecraft:walk_one_cm":4142,"minecraft:leave_game":3,"minecraft:sprint_one_cm":35237,"minecraft:play_time":7090,"minecraft:time_since_death":1178,"minecraft:walk_on_water_one_cm":26,"minecraft:deaths":1,"minecraft:sneak_time":45,"minecraft:total_world_time":7090,"minecraft:mob_kills":1,"minecraft:fly_one_cm":62227},"minecraft:picked_up":{"minecraft:porkchop":3},"minecraft:killed":{"minecraft:pig":1}},"DataVersion":2730}