{"stats":{"minecraft:used":{"minecraft:stone_sword":5,"minecraft:bow":3,"minecraft:leather_helmet":1,"minecraft:iron_sword":10},"minecraft:custom":{"minecraft:time_since_rest":7512,"minecraft:crouch_one_cm":202,"minecraft:play_time":7512,"minecraft:sprint_one_cm":36351,"minecraft:damage_taken":273,"minecraft:walk_one_cm":14549,"minecraft:sneak_time":106,"minecraft:mob_kills":15,"minecraft:interact_with_lectern":1,"minecraft:jump":148,"minecraft:damage_dealt":690,"minecraft:leave_game":3,"minecraft:walk_on_water_one_cm":92,"minecraft:time_since_death":7512,"minecraft:climb_one_cm":16,"minecraft:total_world_time":7512,"minecraft:tune_noteblock":2,"minecraft:fly_one_cm":42935},"minecraft:picked_up":{"minecraft:feather":22,"minecraft:chicken":6,"minecraft:cooked_porkchop":2,"minecraft:porkchop":1,"minecraft:cooked_chicken":13,"minecraft:emerald":18,"minecraft:mutton":1,"minecraft:white_wool":1,"minecraft:egg":14},"minecraft:killed":{"minecraft:sheep":1,"minecraft:pig":1,"minecraft:chicken":13}},"DataVersion":2730}