{"stats":{"minecraft:used":{"minecraft:iron_hoe":72,"minecraft:iron_chestplate":2,"minecraft:stone_sword":2,"minecraft:crossbow":2,"minecraft:leather_helmet":1,"minecraft:iron_sword":71},"minecraft:custom":{"minecraft:time_since_rest":19118,"minecraft:sneak_time":1,"minecraft:play_time":19118,"minecraft:sprint_one_cm":71217,"minecraft:damage_taken":103,"minecraft:walk_one_cm":40561,"minecraft:bell_ring":4,"minecraft:mob_kills":77,"minecraft:interact_with_lectern":1,"minecraft:jump":319,"minecraft:damage_dealt":5630,"minecraft:leave_game":3,"minecraft:walk_on_water_one_cm":2197,"minecraft:time_since_death":19118,"minecraft:total_world_time":19118,"minecraft:fly_one_cm":57970},"minecraft:killed":{"minecraft:pig":50,"minecraft:chicken":27},"minecraft:picked_up":{"minecraft:feather":41,"minecraft:chicken":3,"minecraft:cooked_porkchop":111,"minecraft:porkchop":5,"minecraft:cooked_chicken":36,"minecraft:emerald":63,"minecraft:sugar_cane":94,"minecraft:egg":26}},"DataVersion":2730}