{"stats":{"minecraft:killed":{"minecraft:pig":29,"minecraft:chicken":9},"minecraft:custom":{"minecraft:time_since_rest":9178,"minecraft:crouch_one_cm":2133,"minecraft:play_time":9178,"minecraft:sprint_one_cm":20808,"minecraft:open_enderchest":2,"minecraft:damage_taken":90,"minecraft:walk_one_cm":58160,"minecraft:sneak_time":108,"minecraft:mob_kills":38,"minecraft:interact_with_lectern":1,"minecraft:jump":75,"minecraft:damage_dealt":3042,"minecraft:leave_game":1,"minecraft:time_since_death":9178,"minecraft:walk_on_water_one_cm":219,"minecraft:total_world_time":9178,"minecraft:fly_one_cm":17855},"minecraft:picked_up":{"minecraft:feather":7,"minecraft:cooked_porkchop":45,"minecraft:porkchop":21,"minecraft:cooked_chicken":14,"minecraft:emerald":38,"minecraft:sugar_cane":41,"minecraft:egg":9},"minecraft:used":{"minecraft:stone_hoe":75,"minecraft:iron_hoe":43,"minecraft:stone_sword":15,"minecraft:iron_sword":31}},"DataVersion":2730}