{"stats":{"minecraft:used":{"minecraft:leather_helmet":1,"minecraft:stone_sword":2},"minecraft:custom":{"minecraft:jump":25,"minecraft:time_since_rest":575,"minecraft:damage_dealt":100,"minecraft:leave_game":1,"minecraft:sprint_one_cm":2114,"minecraft:play_time":575,"minecraft:time_since_death":575,"minecraft:walk_one_cm":705,"minecraft:total_world_time":575,"minecraft:mob_kills":1,"minecraft:fly_one_cm":4886},"minecraft:killed":{"minecraft:pig":1},"minecraft:picked_up":{"minecraft:porkchop":1}},"DataVersion":2730}