{"stats":{"minecraft:used":{"minecraft:stone_sword":14,"minecraft:bow":1,"minecraft:leather_helmet":1,"minecraft:iron_sword":35},"minecraft:custom":{"minecraft:time_since_rest":3590,"minecraft:deaths":1,"minecraft:play_time":8059,"minecraft:sprint_one_cm":26922,"minecraft:damage_taken":344,"minecraft:walk_one_cm":23676,"minecraft:sneak_time":2,"minecraft:mob_kills":44,"minecraft:jump":155,"minecraft:damage_dealt":2970,"minecraft:leave_game":6,"minecraft:walk_on_water_one_cm":218,"minecraft:time_since_death":3588,"minecraft:total_world_time":8059,"minecraft:fly_one_cm":25331},"minecraft:killed":{"minecraft:pig":25,"minecraft:chicken":19},"minecraft:picked_up":{"minecraft:feather":17,"minecraft:chicken":19,"minecraft:porkchop":57,"minecraft:emerald":19,"minecraft:egg":19}},"DataVersion":2730}