{"stats":{"minecraft:killed":{"minecraft:pig":3,"minecraft:chicken":15},"minecraft:custom":{"minecraft:time_since_rest":3206,"minecraft:play_time":3206,"minecraft:sprint_one_cm":16712,"minecraft:damage_taken":20,"minecraft:walk_one_cm":17057,"minecraft:mob_kills":18,"minecraft:jump":31,"minecraft:damage_dealt":900,"minecraft:leave_game":1,"minecraft:time_since_death":3206,"minecraft:walk_on_water_one_cm":1086,"minecraft:total_world_time":3206,"minecraft:fly_one_cm":7154},"minecraft:picked_up":{"minecraft:feather":17,"minecraft:chicken":6,"minecraft:cooked_porkchop":7,"minecraft:sweet_berries":6,"minecraft:cooked_chicken":13,"minecraft:emerald":18,"minecraft:egg":15},"minecraft:used":{"minecraft:stone_sword":11,"minecraft:leather_helmet":1,"minecraft:iron_sword":12}},"DataVersion":2730}