{"stats":{"minecraft:used":{"minecraft:stone_sword":79,"minecraft:bow":2,"minecraft:leather_helmet":1},"minecraft:custom":{"minecraft:time_since_rest":98,"minecraft:play_time":5774,"minecraft:sprint_one_cm":29701,"minecraft:walk_one_cm":13998,"minecraft:damage_taken":247,"minecraft:deaths":1,"minecraft:interact_with_anvil":1,"minecraft:mob_kills":40,"minecraft:jump":250,"minecraft:damage_dealt":3212,"minecraft:leave_game":1,"minecraft:time_since_death":97,"minecraft:walk_on_water_one_cm":193,"minecraft:total_world_time":5774,"minecraft:fly_one_cm":37468},"minecraft:picked_up":{"minecraft:brown_wool":1,"minecraft:gray_wool":3,"minecraft:emerald":35,"minecraft:black_wool":2,"minecraft:mutton":59,"minecraft:white_wool":30},"minecraft:killed":{"minecraft:sheep":40}},"DataVersion":2730}