{"stats":{"minecraft:picked_up":{"minecraft:nether_wart":140,"minecraft:feather":34,"minecraft:chicken":27,"minecraft:cooked_porkchop":8,"minecraft:sweet_berries":88,"minecraft:iron_ingot":1,"minecraft:porkchop":49,"minecraft:cooked_chicken":11,"minecraft:emerald":7,"minecraft:sugar_cane":33,"minecraft:egg":34},"minecraft:mined":{"minecraft:sugar_cane":12,"minecraft:nether_wart":51},"minecraft:used":{"minecraft:stone_hoe":51,"minecraft:cooked_chicken":2,"minecraft:iron_hoe":12,"minecraft:stone_sword":66,"minecraft:sweet_berries":8,"minecraft:cooked_porkchop":1,"minecraft:baked_potato":3,"minecraft:iron_sword":11},"minecraft:killed":{"minecraft:zombie":1,"minecraft:pig":26,"minecraft:chicken":32},"minecraft:custom":{"minecraft:time_since_rest":14755,"minecraft:crouch_one_cm":391,"minecraft:walk_one_cm":53683,"minecraft:sprint_one_cm":103273,"minecraft:play_time":17866,"minecraft:damage_taken":657,"minecraft:deaths":1,"minecraft:sneak_time":85,"minecraft:mob_kills":59,"minecraft:jump":276,"minecraft:damage_dealt":4040,"minecraft:leave_game":2,"minecraft:walk_on_water_one_cm":339,"minecraft:time_since_death":14752,"minecraft:total_world_time":17866,"minecraft:climb_one_cm":1812,"minecraft:fly_one_cm":41057}},"DataVersion":2730}