{"stats":{"minecraft:killed":{"minecraft:skeleton":18,"minecraft:zombie":22,"minecraft:pig":72,"minecraft:chicken":30,"minecraft:cow":1},"minecraft:custom":{"minecraft:time_since_rest":68936,"minecraft:open_enderchest":22,"minecraft:sprint_one_cm":90999,"minecraft:damage_taken":1890,"minecraft:walk_one_cm":310682,"minecraft:interact_with_anvil":1,"minecraft:mob_kills":147,"minecraft:damage_dealt":21166,"minecraft:fly_one_cm":13469,"minecraft:crouch_one_cm":30,"minecraft:play_time":68936,"minecraft:sneak_time":194,"minecraft:walk_under_water_one_cm":170,"minecraft:interact_with_lectern":1,"minecraft:jump":288,"minecraft:interact_with_grindstone":1,"minecraft:leave_game":4,"minecraft:walk_on_water_one_cm":1906,"minecraft:time_since_death":68936,"minecraft:climb_one_cm":2825,"minecraft:total_world_time":68936,"minecraft:fish_caught":3},"minecraft:picked_up":{"minecraft:cooked_beef":1,"minecraft:feather":43,"minecraft:chicken":14,"minecraft:cooked_porkchop":123,"minecraft:sweet_berries":5,"minecraft:porkchop":45,"minecraft:arrow":23,"minecraft:bone":25,"minecraft:rotten_flesh":37,"minecraft:bow":2,"minecraft:cooked_chicken":27,"minecraft:emerald":82,"minecraft:sugar_cane":107,"minecraft:cod":3,"minecraft:egg":39},"minecraft:mined":{"minecraft:sugar_cane":69},"minecraft:used":{"minecraft:iron_hoe":69,"minecraft:stone_sword":54,"minecraft:iron_sword":175,"minecraft:cooked_chicken":1,"minecraft:fishing_rod":10,"minecraft:bow":15,"minecraft:cooked_porkchop":20,"minecraft:cooked_beef":1}},"DataVersion":2730}